{"list":" resume yui-gc yui-u first me2 contact-info yui-b yui-gf h enlarge i talent a b c j job d last e k f g text-gray-500 header container flex flex-wrap items-center justify-between mx-auto px-4 py-5 font-bold font-serif hover:text-opacity-75 inline-flex leading-none space-x-1 text-black text-xl uppercase bg-yellow-800 hover:text-white lg:hidden px-3 py-2 rounded bg-yellow-300 block border-b-2 border-current my-1 w-6 border-t flex-grow hidden mt-5 pt-3 w-full lg:border-t-0 lg:flex lg:items-center lg:mt-0 lg:pl-10 lg:pt-0 lg:space-x-4 lg:space-y-0 lg:w-auto flex-col lg:flex-row hover:underline lg:px-4 px-0 gap-2 justify-center lg:inline-flex lg:w-40 bg-opacity-50 bg-yellow-600 border-2 border-gray-300 bounceIcon fill-red-300 p-1 wrap arrow slide slide1 slide-content slide2 slide3 slide4 bg-gradient-to-t bg-gray-300 from-white h-screen poster relative text-center to-gray-400 via-gray-200 pb-24 pt-36 lg:pt-48 -mx-4 space-y-6 md:w-10/12 xl:w-7/12 bg-white mb-6 p-2 rounded-full shadow-xl w-1/2 mb-2 text-4xl text-gray-900 md:leading-tight lg:leading-tight lg:text-5xl space-x-2 nowrap bg-primary-500 h-px max-w-full opacity-25 px-10 w-auto section1 p-8 lg:w-8/12 me xl:mt-5 xl:text-lg photo1 photo2 photo3 photo4 photo5 photo -mx-2 max-w-sm overflow-hidden rounded-lg shadow-md duration-300 hover:scale-105 hover:shadow-xl mt-8 h-16 w-16 text-green-400 mt-2 text-2xl my-4 text-sm space-x-4 bg-gray-100 py-4 inline-block rounded-md bg-green-500 px-6 font-semibold text-green-100 duration-75 hover:bg-green-400 p-4 lg:w-4/12 rounded-xl saturate-50 pb-12 pt-5 text-3xl text-primary-500 mt-10 py-12 lg:p-12 lg:mx-auto lg:w-7/12 section2 2xl:inset-x-full left-full lg:pt-100 lg:px-100 px-5 mb-12 text-gray-400 text-opacity-90 -m-1 md:-m-2 md:p-2 object-cover object-center h-full md:p-1/2 pgia-slider 2xl:w-6/12 pgia-slides-container pgia-slide -translate-x-1/2 absolute left-1/2 p-5 text-gray-50 top-3 lg:text-xl xl:text-xl right-5 bottom-3 lg:text-l pgia-controls prev pgia-control pgia-pagination pgia-pagination-item next pgia-progress pgia-progress-bar works section no-padding container-fluid row no-gutter col-lg-2 col-md-4 col-sm-4 work work-box overlay overlay-caption fa fa-search-plus fa-2x section3 pt-24 lg:w-10/12 2xl:w-8/12 bg-gray-900 bg-opacity-90 font-light pb-6 pt-12 leading-relaxed md:divide-gray-300 md:divide-x md:w-4/12 gap-3 lg:px-8 bg-gray-600 p-3 text-color4-300 lg:p-5 h-8 w-8 sm:h-10 sm:w-10 lg:h-12 lg:w-12 text-lg lg:pl-8 lg:pr-6 md:text-center hover:text-color4-300","map":{"resume":true,"yui-gc":true,"yui-u":true,"first":true,"me2":true,"contact-info":true,"yui-b":true,"yui-gf":true,"h":true,"enlarge":true,"i":true,"talent":true,"a":true,"b":true,"c":true,"j":true,"job":true,"d":true,"last":true,"e":true,"k":true,"f":true,"g":true,"text-gray-500":true,"header":true,"container":true,"flex":true,"flex-wrap":true,"items-center":true,"justify-between":true,"mx-auto":true,"px-4":true,"py-5":true,"font-bold":true,"font-serif":true,"hover:text-opacity-75":true,"inline-flex":true,"leading-none":true,"space-x-1":true,"text-black":true,"text-xl":true,"uppercase":true,"bg-yellow-800":true,"hover:text-white":true,"lg:hidden":true,"px-3":true,"py-2":true,"rounded":true,"bg-yellow-300":true,"block":true,"border-b-2":true,"border-current":true,"my-1":true,"w-6":true,"border-t":true,"flex-grow":true,"hidden":true,"mt-5":true,"pt-3":true,"w-full":true,"lg:border-t-0":true,"lg:flex":true,"lg:items-center":true,"lg:mt-0":true,"lg:pl-10":true,"lg:pt-0":true,"lg:space-x-4":true,"lg:space-y-0":true,"lg:w-auto":true,"flex-col":true,"lg:flex-row":true,"hover:underline":true,"lg:px-4":true,"px-0":true,"gap-2":true,"justify-center":true,"lg:inline-flex":true,"lg:w-40":true,"bg-opacity-50":true,"bg-yellow-600":true,"border-2":true,"border-gray-300":true,"bounceIcon":true,"fill-red-300":true,"p-1":true,"wrap":true,"arrow":true,"slide":true,"slide1":true,"slide-content":true,"slide2":true,"slide3":true,"slide4":true,"bg-gradient-to-t":true,"bg-gray-300":true,"from-white":true,"h-screen":true,"poster":true,"relative":true,"text-center":true,"to-gray-400":true,"via-gray-200":true,"pb-24":true,"pt-36":true,"lg:pt-48":true,"-mx-4":true,"space-y-6":true,"md:w-10/12":true,"xl:w-7/12":true,"bg-white":true,"mb-6":true,"p-2":true,"rounded-full":true,"shadow-xl":true,"w-1/2":true,"mb-2":true,"text-4xl":true,"text-gray-900":true,"md:leading-tight":true,"lg:leading-tight":true,"lg:text-5xl":true,"space-x-2":true,"nowrap":true,"bg-primary-500":true,"h-px":true,"max-w-full":true,"opacity-25":true,"px-10":true,"w-auto":true,"section1":true,"p-8":true,"lg:w-8/12":true,"me":true,"xl:mt-5":true,"xl:text-lg":true,"photo1":true,"photo2":true,"photo3":true,"photo4":true,"photo5":true,"photo":true,"-mx-2":true,"max-w-sm":true,"overflow-hidden":true,"rounded-lg":true,"shadow-md":true,"duration-300":true,"hover:scale-105":true,"hover:shadow-xl":true,"mt-8":true,"h-16":true,"w-16":true,"text-green-400":true,"mt-2":true,"text-2xl":true,"my-4":true,"text-sm":true,"space-x-4":true,"bg-gray-100":true,"py-4":true,"inline-block":true,"rounded-md":true,"bg-green-500":true,"px-6":true,"font-semibold":true,"text-green-100":true,"duration-75":true,"hover:bg-green-400":true,"p-4":true,"lg:w-4/12":true,"rounded-xl":true,"saturate-50":true,"pb-12":true,"pt-5":true,"text-3xl":true,"text-primary-500":true,"mt-10":true,"py-12":true,"lg:p-12":true,"lg:mx-auto":true,"lg:w-7/12":true,"section2":true,"2xl:inset-x-full":true,"left-full":true,"lg:pt-100":true,"lg:px-100":true,"px-5":true,"mb-12":true,"text-gray-400":true,"text-opacity-90":true,"-m-1":true,"md:-m-2":true,"md:p-2":true,"object-cover":true,"object-center":true,"h-full":true,"md:p-1/2":true,"pgia-slider":true,"2xl:w-6/12":true,"pgia-slides-container":true,"pgia-slide":true,"-translate-x-1/2":true,"absolute":true,"left-1/2":true,"p-5":true,"text-gray-50":true,"top-3":true,"lg:text-xl":true,"xl:text-xl":true,"right-5":true,"bottom-3":true,"lg:text-l":true,"pgia-controls":true,"prev":true,"pgia-control":true,"pgia-pagination":true,"pgia-pagination-item":true,"next":true,"pgia-progress":true,"pgia-progress-bar":true,"works":true,"section":true,"no-padding":true,"container-fluid":true,"row":true,"no-gutter":true,"col-lg-2":true,"col-md-4":true,"col-sm-4":true,"work":true,"work-box":true,"overlay":true,"overlay-caption":true,"fa":true,"fa-search-plus":true,"fa-2x":true,"section3":true,"pt-24":true,"lg:w-10/12":true,"2xl:w-8/12":true,"bg-gray-900":true,"bg-opacity-90":true,"font-light":true,"pb-6":true,"pt-12":true,"leading-relaxed":true,"md:divide-gray-300":true,"md:divide-x":true,"md:w-4/12":true,"gap-3":true,"lg:px-8":true,"bg-gray-600":true,"p-3":true,"text-color4-300":true,"lg:p-5":true,"h-8":true,"w-8":true,"sm:h-10":true,"sm:w-10":true,"lg:h-12":true,"lg:w-12":true,"text-lg":true,"lg:pl-8":true,"lg:pr-6":true,"md:text-center":true,"hover:text-color4-300":true}}